atenpdu/__init__.py
atenpdu/mibs/ATEN-PE-CFG.py
atenpdu/pductl.py
atenpdu-0.7.2.dist-info/METADATA
atenpdu-0.7.2.dist-info/WHEEL
atenpdu-0.7.2.dist-info/entry_points.txt
atenpdu-0.7.2.dist-info/licenses/LICENSE
atenpdu-0.7.2.dist-info/RECORD
