Metadata-Version: 2.4
Name: atenpdu
Version: 0.7.2
Summary: Interface for ATEN-PE PDUs
License-Expression: MIT
License-File: LICENSE
Author: Andreas Oberritter
Author-email: obi@saftware.de
Requires-Python: >=3.9.2,<4.0.0
Classifier: Development Status :: 4 - Beta
Classifier: Intended Audience :: Developers
Classifier: Intended Audience :: System Administrators
Classifier: Operating System :: OS Independent
Classifier: Topic :: Home Automation
Classifier: Topic :: Software Development :: Libraries :: Python Modules
Classifier: Topic :: System :: Systems Administration
Classifier: Topic :: Utilities
Requires-Dist: async-timeout (>=4.0.3,<5.0.0)
Requires-Dist: cryptography (>=46.0.2)
Requires-Dist: pysnmp (>=7.1.21,<8.0.0)
Project-URL: Repository, https://github.com/mtdcr/pductl
